LICENSE
youtrack/__init__.py
youtrack/config.py
youtrack/connection.py
youtrack/import_helper.py
youtrack/youtrack.py
test_dohq_youtrack-0.2.2.dist-info/LICENSE
test_dohq_youtrack-0.2.2.dist-info/METADATA
test_dohq_youtrack-0.2.2.dist-info/WHEEL
test_dohq_youtrack-0.2.2.dist-info/top_level.txt
test_dohq_youtrack-0.2.2.dist-info/zip-safe
test_dohq_youtrack-0.2.2.dist-info/RECORD
