Metadata-Version: 2.1
Name: test-dohq-youtrack
Version: 0.2.2
Summary: YouTrack Python 3 Client Library
Home-page: https://devopshq.github.io/youtrack/
Author: Alexander Kovalev
Author-email: ak@alkov.pro
License: MIT License
Download-URL: https://github.com/devopshq/youtrack
Keywords: tracker,youtrack
Platform: UNKNOWN
Classifier: Development Status :: 4 - Beta
Classifier: Intended Audience :: Developers
Classifier: Topic :: Software Development :: Libraries
Classifier: License :: OSI Approved :: MIT License
Classifier: Operating System :: OS Independent
Classifier: Programming Language :: Python :: 3
Classifier: Programming Language :: Python :: 3.1
Classifier: Programming Language :: Python :: 3.2
Classifier: Programming Language :: Python :: 3.3
Classifier: Programming Language :: Python :: 3.4
Classifier: Programming Language :: Python :: 3.5
Classifier: Programming Language :: Python :: 3.6
Requires-Dist: httplib2
